{
  "threat_id": "T011",
  "user_id": "user_smart_11",
  "device_id": "Antivirus",
  "detected_at": "2025-10-15T17:45:00Z",
  "threat_type": "Loss of support services",
  "threat_description": "Licencia de antivirus vencida sin actualización",
  "severity": "grave",
  "actions_taken": "Renovar licencia y actualizar definiciones de virus",
  "status": "resolved",
  "project_name": "SmartHome",
  "subproject_name": "SmartHome",
  "cause": "Falta de monitoreo de renovación de licencias",
  "controls": "A.16.01;A.16.02"
}
